SkillsManager/SkillsManager.py
SkillsManager/__init__.py
SkillsManager/SMLoader/Loader.py
SkillsManager/SMLoader/__init__.py
SkillsManager/SMPackageManager/PackageManager.py
SkillsManager/SMPackageManager/__init__.py
SkillsManager/SMParsers/Parsers.py
SkillsManager/SMParsers/__init__.py
SkillsManager/SMParsers/ActionParser/ActionParser.py
SkillsManager/SMParsers/ActionParser/__init__.py
SkillsManager/SMParsers/ArgumentParser/ArgumentParser.py
SkillsManager/SMParsers/ArgumentParser/__init__.py
SkillsManager/SMParsers/SkillParser/SkillParser.py
SkillsManager/SMParsers/SkillParser/__init__.py
SkillsManager/SMParsers/ToolParser/ToolParser.py
SkillsManager/SMParsers/ToolParser/__init__.py
SkillsManager/SMSkillMover/SkillMover.py
SkillsManager/SMSkillMover/__init__.py
SkillsManager/SMUtils/Utils.py
SkillsManager/SMUtils/__init__.py
skillsmanager-0.2.3.dist-info/METADATA
skillsmanager-0.2.3.dist-info/WHEEL
skillsmanager-0.2.3.dist-info/top_level.txt
skillsmanager-0.2.3.dist-info/RECORD
