Metadata-Version: 2.4
Name: SkillsManager
Version: 0.2.3
Summary: Modern manager for AI skills, tools, loading, execution, and automation.
Author: Tristan McBride Sr.
Author-email: "Tristan McBride Sr." <142635792+TristanMcBrideSr@users.noreply.github.com>
Maintainer-email: "Tristan McBride Sr." <142635792+TristanMcBrideSr@users.noreply.github.com>
License-Expression: Apache-2.0
Project-URL: Homepage, https://github.com/TristanMcBrideSr
Keywords: AI,Agents,Skills,Tools,Autoload,Productivity,Automation
Classifier: Programming Language :: Python :: 3
Classifier: Operating System :: OS Independent
Classifier: Intended Audience :: Developers
Requires-Python: >=3.10
Requires-Dist: pyperclip
Requires-Dist: pyautogui
Requires-Dist: python-dotenv
Requires-Dist: google-genai
Requires-Dist: uv
Requires-Dist: SkillLink
Requires-Dist: SyncLink
Requires-Dist: SynMem
Requires-Dist: SynLrn
Requires-Dist: BitSig
Requires-Dist: requests
Dynamic: author
